examples/__init__.py
examples/advanced_extraction_demo.py
examples/advanced_vector_search_demo.py
examples/analytics_reporting_demo.py
examples/audio_transcription_demo.py
examples/basic_completion.py
examples/browser_automation_demo.py
examples/cache_demo.py
examples/claude_integration_demo.py
examples/compare_synthesize_demo.py
examples/cost_optimization.py
examples/document_processing.py
examples/entity_relation_graph_demo.py
examples/filesystem_operations_demo.py
examples/grok_integration_demo.py
examples/html_to_markdown_demo.py
examples/marqo_fused_search_demo.py
examples/measure_model_speeds.py
examples/meta_api_demo.py
examples/multi_provider_demo.py
examples/prompt_templates_demo.py
examples/rag_example.py
examples/research_workflow_demo.py
examples/simple_completion_demo.py
examples/sql_database_interactions_demo.py
examples/sse_client_demo.py
examples/test_code_extraction.py
examples/text_classification_demo.py
examples/text_redline_demo.py
examples/tournament_code_demo.py
examples/tournament_text_demo.py
examples/vector_search_demo.py
examples/web_automation_instruction_packs.py
examples/workflow_delegation_demo.py
examples/data/Steve_Jobs_Introducing_The_iPhone_compressed.md
examples/data/Steve_Jobs_Introducing_The_iPhone_compressed.mp3
examples/data/sample_event.txt
examples/sample/article.txt
examples/sample/legal_contract.txt
examples/sample/medical_case.txt
examples/sample/research_paper.txt
examples/sample/text_classification_samples/email_classification.txt
examples/sample/text_classification_samples/news_samples.txt
examples/sample/text_classification_samples/product_reviews.txt
examples/sample/text_classification_samples/support_tickets.txt
llm_gateway/__init__.py
llm_gateway/__main__.py
llm_gateway/config.py
llm_gateway/constants.py
llm_gateway/exceptions.py
llm_gateway/server.py
llm_gateway/cli/__init__.py
llm_gateway/cli/commands.py
llm_gateway/cli/helpers.py
llm_gateway/cli/main.py
llm_gateway/clients/__init__.py
mseep_llm_gateway_mcp_server-0.1.0.dist-info/METADATA
mseep_llm_gateway_mcp_server-0.1.0.dist-info/WHEEL
mseep_llm_gateway_mcp_server-0.1.0.dist-info/entry_points.txt
mseep_llm_gateway_mcp_server-0.1.0.dist-info/licenses/LICENSE
mseep_llm_gateway_mcp_server-0.1.0.dist-info/RECORD
