Metadata-Version: 2.4
Name: mseep-llm_gateway_mcp_server
Version: 0.1.0
Summary: A Model Context Protocol (MCP) server providing unified access to multiple LLM providers with cost optimization
Project-URL: Homepage, https://github.com/Dicklesworthstone/llm_gateway_mcp_server
Project-URL: Documentation, https://github.com/Dicklesworthstone/llm_gateway_mcp_server/docs
Project-URL: Repository, https://github.com/Dicklesworthstone/llm_gateway_mcp_server.git
Project-URL: Bug Reports, https://github.com/Dicklesworthstone/llm_gateway_mcp_server/issues
Author-email: Jeffrey Emanuel <jeffrey.emanuel@gmail.com>
Maintainer-email: Jeffrey Emanuel <jeffrey.emanuel@gmail.com>
License: MIT License
License-File: LICENSE
Keywords: ai,claude,deepseek,gateway,gemini,gpt,llm,mcp
Classifier: Development Status :: 3 - Alpha
Classifier: Intended Audience :: Developers
Classifier: License :: OSI Approved :: MIT License
Classifier: Programming Language :: Python :: 3.13
Classifier: Topic :: Scientific/Engineering :: Artificial Intelligence
Requires-Python: >=3.13
Requires-Dist: aiofiles
Requires-Dist: aiosqlite
Requires-Dist: anthropic
Requires-Dist: asyncio
Requires-Dist: beautifulsoup4
Requires-Dist: chromadb
Requires-Dist: colorama
Requires-Dist: diskcache
Requires-Dist: faster-whisper
Requires-Dist: fitz
Requires-Dist: google-genai
Requires-Dist: html2text
Requires-Dist: httpx
Requires-Dist: jinja2
Requires-Dist: jsonschema
Requires-Dist: lxml
Requires-Dist: markdown
Requires-Dist: markdownify
Requires-Dist: marqo
Requires-Dist: matplotlib
Requires-Dist: mcp
Requires-Dist: msgpack
Requires-Dist: numpy
Requires-Dist: openai
Requires-Dist: opencv-python
Requires-Dist: pandas
Requires-Dist: pdf2image
Requires-Dist: pdfplumber
Requires-Dist: pillow
Requires-Dist: prometheus-client
Requires-Dist: pydantic
Requires-Dist: pydantic-settings
Requires-Dist: pymupdf
Requires-Dist: pytesseract
Requires-Dist: pytest-playwright
Requires-Dist: python-decouple
Requires-Dist: python-docx
Requires-Dist: python-slugify
Requires-Dist: pyvis
Requires-Dist: readability-lxml
Requires-Dist: rich
Requires-Dist: sentence-transformers
Requires-Dist: sqlalchemy
Requires-Dist: tenacity
Requires-Dist: tiktoken
Requires-Dist: tqdm
Requires-Dist: trafilatura
Requires-Dist: xmldiff
Provides-Extra: advanced
Requires-Dist: accelerate; extra == 'advanced'
Requires-Dist: flash-attn; extra == 'advanced'
Requires-Dist: torch; extra == 'advanced'
Requires-Dist: torchaudio; extra == 'advanced'
Requires-Dist: torchvision; extra == 'advanced'
Requires-Dist: transformers; extra == 'advanced'
Provides-Extra: all
Requires-Dist: llm-gateway-mcp-server[advanced,dev,docs]; extra == 'all'
Provides-Extra: dev
Requires-Dist: isort; extra == 'dev'
Requires-Dist: mypy; extra == 'dev'
Requires-Dist: pre-commit; extra == 'dev'
Requires-Dist: pytest; extra == 'dev'
Requires-Dist: pytest-asyncio; extra == 'dev'
Requires-Dist: pytest-cov; extra == 'dev'
Requires-Dist: ruff; extra == 'dev'
Requires-Dist: types-aiofiles; extra == 'dev'
Provides-Extra: docs
Requires-Dist: mkdocs; extra == 'docs'
Requires-Dist: mkdocs-material; extra == 'docs'
Requires-Dist: mkdocstrings; extra == 'docs'
Requires-Dist: mkdocstrings-python; extra == 'docs'
